{
  "https://www.patanjaliayurved.net/category/paridhan/236" : {
    "transaction" : "https://www.patanjaliayurved.net/category/paridhan/236",
    "sampleCount" : 10,
    "errorCount" : 0,
    "errorPct" : 0.0,
    "meanResTime" : 1963.0,
    "medianResTime" : 2030.0,
    "minResTime" : 1809.0,
    "maxResTime" : 2071.0,
    "pct1ResTime" : 2070.2,
    "pct2ResTime" : 2071.0,
    "pct3ResTime" : 2071.0,
    "throughput" : 3.486750348675035,
    "receivedKBytesPerSec" : 990.8057389731521,
    "sentKBytesPerSec" : 2.100903286262204
  },
  "https://www.patanjaliayurved.net/search/aluvera" : {
    "transaction" : "https://www.patanjaliayurved.net/search/aluvera",
    "sampleCount" : 10,
    "errorCount" : 0,
    "errorPct" : 0.0,
    "meanResTime" : 2347.6000000000004,
    "medianResTime" : 2262.5,
    "minResTime" : 1859.0,
    "maxResTime" : 3036.0,
    "pct1ResTime" : 3000.8,
    "pct2ResTime" : 3036.0,
    "pct3ResTime" : 3036.0,
    "throughput" : 3.1625553447185326,
    "receivedKBytesPerSec" : 1272.1008262175837,
    "sentKBytesPerSec" : 1.5998082700822265
  },
  "Test" : {
    "transaction" : "Test",
    "sampleCount" : 10,
    "errorCount" : 0,
    "errorPct" : 0.0,
    "meanResTime" : 13025.999999999998,
    "medianResTime" : 12964.5,
    "minResTime" : 12479.0,
    "maxResTime" : 13719.0,
    "pct1ResTime" : 13705.2,
    "pct2ResTime" : 13719.0,
    "pct3ResTime" : 13719.0,
    "throughput" : 0.7190106413574922,
    "receivedKBytesPerSec" : 1262.278651450604,
    "sentKBytesPerSec" : 2.996111725266034
  },
  "Total" : {
    "transaction" : "Total",
    "sampleCount" : 70,
    "errorCount" : 0,
    "errorPct" : 0.0,
    "meanResTime" : 1860.8571428571424,
    "medianResTime" : 1772.5,
    "minResTime" : 1355.0,
    "maxResTime" : 3036.0,
    "pct1ResTime" : 2502.7,
    "pct2ResTime" : 2633.9500000000003,
    "pct3ResTime" : 3036.0,
    "throughput" : 0.9560229445506692,
    "receivedKBytesPerSec" : 239.76743354786944,
    "sentKBytesPerSec" : 0.5691057344304835
  },
  "https://www.patanjaliayurved.net/product/paridhan/spiritual/vignharta-kvach-paudjwkkvs1915158/3610" : {
    "transaction" : "https://www.patanjaliayurved.net/product/paridhan/spiritual/vignharta-kvach-paudjwkkvs1915158/3610",
    "sampleCount" : 20,
    "errorCount" : 0,
    "errorPct" : 0.0,
    "meanResTime" : 1765.3500000000004,
    "medianResTime" : 1763.0,
    "minResTime" : 1740.0,
    "maxResTime" : 1791.0,
    "pct1ResTime" : 1790.5,
    "pct2ResTime" : 1791.0,
    "pct3ResTime" : 1791.0,
    "throughput" : 1.1751571772724603,
    "receivedKBytesPerSec" : 250.10420339032848,
    "sentKBytesPerSec" : 0.7585731388448206
  },
  "https://www.patanjaliayurved.net/checkout" : {
    "transaction" : "https://www.patanjaliayurved.net/checkout",
    "sampleCount" : 10,
    "errorCount" : 0,
    "errorPct" : 0.0,
    "meanResTime" : 1386.0,
    "medianResTime" : 1387.5,
    "minResTime" : 1371.0,
    "maxResTime" : 1419.0,
    "pct1ResTime" : 1416.2,
    "pct2ResTime" : 1419.0,
    "pct3ResTime" : 1419.0,
    "throughput" : 4.675081813931744,
    "receivedKBytesPerSec" : 482.5332734338476,
    "sentKBytesPerSec" : 2.7575677886863024
  },
  "https://www.patanjaliayurved.net/customer/login" : {
    "transaction" : "https://www.patanjaliayurved.net/customer/login",
    "sampleCount" : 10,
    "errorCount" : 0,
    "errorPct" : 0.0,
    "meanResTime" : 1384.6,
    "medianResTime" : 1384.5,
    "minResTime" : 1355.0,
    "maxResTime" : 1414.0,
    "pct1ResTime" : 1413.0,
    "pct2ResTime" : 1414.0,
    "pct3ResTime" : 1414.0,
    "throughput" : 4.151100041511,
    "receivedKBytesPerSec" : 421.35286944790374,
    "sentKBytesPerSec" : 2.472823266915733
  },
  "https://www.patanjaliayurved.net/" : {
    "transaction" : "https://www.patanjaliayurved.net/",
    "sampleCount" : 10,
    "errorCount" : 0,
    "errorPct" : 0.0,
    "meanResTime" : 2414.1000000000004,
    "medianResTime" : 2400.0,
    "minResTime" : 2243.0,
    "maxResTime" : 2703.0,
    "pct1ResTime" : 2685.6,
    "pct2ResTime" : 2703.0,
    "pct3ResTime" : 2703.0,
    "throughput" : 3.0358227079538556,
    "receivedKBytesPerSec" : 1332.1361993397086,
    "sentKBytesPerSec" : 1.7669436854887675
  }
}